Metadata-Version: 2.1
Name: humannotator
Version: 0.0.3
Summary: Customizable tool for easy manual annotation
Home-page: http://github.com/lcvriend/humannotator
Author: L.C. Vriend, D.E. Kim
Author-email: vanboefer@gmail.com
License: GPLv3+
Keywords: annotation annotator text data pandas
Platform: UNKNOWN
Classifier: Development Status :: 3 - Alpha
Classifier: Intended Audience :: Science/Research
Classifier: License :: OSI Approved :: GNU General Public License v3 or later (GPLv3+)
Classifier: Programming Language :: Python :: 3.7
Classifier: Topic :: Scientific/Engineering :: Information Analysis
Classifier: Topic :: Text Processing :: Linguistic
Classifier: Topic :: Utilities
Requires-Python: >=3.6
Requires-Dist: pandas (>=0.24.0)
Requires-Dist: markdown
